README.md
__init__.py
main.py
mts.py
setup.py
mintty_theme_selector.egg-info/PKG-INFO
mintty_theme_selector.egg-info/SOURCES.txt
mintty_theme_selector.egg-info/dependency_links.txt
mintty_theme_selector.egg-info/entry_points.txt
mintty_theme_selector.egg-info/top_level.txt