Metadata-Version: 2.1
Name: mintty-theme-selector
Version: 1.0.2
Summary: Command-line theme selector for mintty
Home-page: https://github.com/kohanyirobert/mintty-theme-selector
Author: Kohányi Róbert
Author-email: kohanyi.robert@gmail.com
License: WTFPL
Keywords: mintty theme command-line
Platform: UNKNOWN
Requires-Python: >=3
